hitchrunpy/__init__.py
hitchrunpy/example_python_code.py
hitchrunpy/exceptions.py
hitchrunpy/templates/base.jinja2
hitchrunpy-0.11.3.dist-info/LICENSE.txt
hitchrunpy-0.11.3.dist-info/METADATA
hitchrunpy-0.11.3.dist-info/WHEEL
hitchrunpy-0.11.3.dist-info/top_level.txt
hitchrunpy-0.11.3.dist-info/RECORD
