Metadata-Version: 2.1
Name: hitchrunpy
Version: 0.11.3
Summary: Run and interact with snippets of python code.
Home-page: https://github.com/hitchtest/hitchrunpy
Author: Colm O'Connor
Author-email: Colm O'Connor <colm.oconnor.github@gmail.com>
License: MIT
Project-URL: homepage, https://hitchdev.com/hitchrunpy
Project-URL: documentation, https://hitchdev.com/hitchrunpy/using
Project-URL: repository, https://github.com/hitchdev/hitchrunpy
Project-URL: changelog, https://hitchdev.com/hitchrunpy/changelog
Keywords: test,python
Classifier: Programming Language :: Python :: 3
Classifier: License :: OSI Approved :: MIT License
Classifier: Topic :: Software Development :: Testing
Classifier: Topic :: Software Development :: Libraries
Classifier: Natural Language :: English
Requires-Python: >=3.7.0
License-File: LICENSE.txt
Requires-Dist: jinja2 (>=2.10)
Requires-Dist: prettystack (>=0.2.7)
Requires-Dist: path.py (>=9.0)
Requires-Dist: icommandlib (>=0.6.0)
Requires-Dist: commandlib (>=0.3.5)
